pywry_nightly-0.6.1.dev20230917.dist-info/METADATA
pywry_nightly-0.6.1.dev20230917.dist-info/WHEEL
pywry_nightly-0.6.1.dev20230917.dist-info/license_files/LICENSE
pywry/backend.py
pywry/core.py
pywry/py.typed
pywry/pywry.pyi
pywry/__init__.py
pywry_nightly-0.6.1.dev20230917.data/scripts/pywry.exe
pywry_nightly-0.6.1.dev20230917.dist-info/RECORD
