Metadata-Version: 2.1
Name: pywry-nightly
Version: 0.6.1.dev20230917
Classifier: Programming Language :: Rust
Classifier: Programming Language :: Python :: Implementation :: CPython
Classifier: Programming Language :: Python :: Implementation :: PyPy
Classifier: Operating System :: POSIX
Classifier: Operating System :: Microsoft :: Windows
Classifier: Operating System :: MacOS
Requires-Dist: setproctitle
Requires-Dist: auditwheel; extra == 'dev'
Requires-Dist: wheel; extra == 'dev'
Provides-Extra: dev
License-File: LICENSE
Requires-Python: >=3.8
